mcp_server_reddit/__init__.py
mcp_server_reddit/__main__.py
mcp_server_reddit/server.py
iflow_mcp_mcp_server_reddit-0.2.0.dist-info/METADATA
iflow_mcp_mcp_server_reddit-0.2.0.dist-info/WHEEL
iflow_mcp_mcp_server_reddit-0.2.0.dist-info/entry_points.txt
iflow_mcp_mcp_server_reddit-0.2.0.dist-info/licenses/LICENSE
iflow_mcp_mcp_server_reddit-0.2.0.dist-info/RECORD
