Metadata-Version: 2.4
Name: iflow-mcp_mcp-server-reddit
Version: 0.2.0
Summary: A Model Context Protocol (MCP) server that provides tools for fetching Reddit content, including frontpage posts, subreddit information and hot posts, post details, and comments.
Author-email: Hawstein <hawstein@claudemind.com>
License: MIT
License-File: LICENSE
Keywords: llm,mcp,reddit
Classifier: Development Status :: 4 - Beta
Classifier: Intended Audience :: Developers
Classifier: License :: OSI Approved :: MIT License
Classifier: Programming Language :: Python :: 3
Classifier: Programming Language :: Python :: 3.11
Requires-Python: >=3.11
Requires-Dist: mcp>=1.0.0
Requires-Dist: pydantic>=2.0.0
Requires-Dist: redditwarp>=1.3.0
